LICENSE
README.md
setup.py
kzw_fib_py/__init__.py
kzw_fib_py/version.py
kzw_fib_py.egg-info/PKG-INFO
kzw_fib_py.egg-info/SOURCES.txt
kzw_fib_py.egg-info/dependency_links.txt
kzw_fib_py.egg-info/entry_points.txt
kzw_fib_py.egg-info/requires.txt
kzw_fib_py.egg-info/top_level.txt
kzw_fib_py/cmd/__init__.py
kzw_fib_py/cmd/fib_numb.py
kzw_fib_py/fib_calcs/__init__.py
kzw_fib_py/fib_calcs/fib_number.py
kzw_fib_py/fib_calcs/fib_numbers.py
tests/kzw_fib_py/__init__.py
tests/kzw_fib_py/fib_calcs/__init__.py
tests/kzw_fib_py/fib_calcs/test_fib_number.py
tests/kzw_fib_py/fib_calcs/test_fib_numbers.py